[
  {
    "CustomerID": "e526775a-b370-5a20-8350-ee7b596af4f4",
    "Department": "IT",
    "Email": "a.schmidt@techcorp.de",
    "FirstName": "Anna",
    "ID": "7a5c108c-2c0b-5e11-8a63-34d84bcc4e65",
    "LastName": "Schmidt",
    "Phone": "+49 89 12345-202",
    "Position": "IT-Leiterin"
  },
  {
    "CustomerID": "e526775a-b370-5a20-8350-ee7b596af4f4",
    "Department": "Einkauf",
    "Email": "m.mueller@techcorp.de",
    "FirstName": "Max",
    "ID": "a32253e5-dbf2-5c1a-96e8-fd944ead113b",
    "LastName": "Müller",
    "Phone": "+49 89 12345-101",
    "Position": "Einkaufsleiter"
  },
  {
    "CustomerID": "0066acd3-3d2f-573a-abd0-f4f2ea728695",
    "Department": "Vertrieb",
    "Email": "h.weber@periphtech.ch",
    "FirstName": "Hans",
    "ID": "945db6c6-e16a-58bb-814c-7bc473b84a3a",
    "LastName": "Weber",
    "Phone": "+41 44 987-6001",
    "Position": "Key Account Manager"
  },
  {
    "CustomerID": "640987dd-2c2e-575b-b764-4ede52acbd0f",
    "Department": "Technik",
    "Email": "k.fischer@displaymax.de",
    "FirstName": "Klaus",
    "ID": "f0a3b41b-b4ee-5e17-8c88-e7e87c8f2792",
    "LastName": "Fischer",
    "Phone": "+49 30 55667-801",
    "Position": "Technischer Leiter"
  },
  {
    "CustomerID": "40eceb19-2bbe-5570-bcc2-b3e638e325d8",
    "Department": "Procurement",
    "Email": "s.johnson@connectworld.co.uk",
    "FirstName": "Sarah",
    "ID": "66a068f4-2869-5968-b78d-83bde853eaaa",
    "LastName": "Johnson",
    "Phone": "+44 20 7946-1234",
    "Position": "Senior Buyer"
  },
  {
    "CustomerID": "abe7e76f-193f-5c64-b3e7-6352ad62139d",
    "Department": "Geschäftsführung",
    "Email": "e.berger@lightdesign.at",
    "FirstName": "Eva",
    "ID": "8fb72d13-0b3c-5500-bdde-5412dd277be6",
    "LastName": "Berger",
    "Phone": "+43 1 234-5679",
    "Position": "Geschäftsführerin"
  },
  {
    "ID": "d2c2e63c-c19e-589d-91ba-5622c83adbd8",
    "CustomerID": "e526775a-b370-5a20-8350-ee7b596af4f4",
    "FirstName": "Maria",
    "LastName": "Schmidt",
    "Position": "IT-Projektleiterin",
    "Department": "IT-Projekte",
    "Email": "m.schmidt@techcorp.de",
    "Phone": "+49 89 12345-301"
  },
  {
    "ID": "f046bb00-857d-5985-9b7a-cd9d84e28ed4",
    "CustomerID": "e526775a-b370-5a20-8350-ee7b596af4f4",
    "FirstName": "Thomas",
    "LastName": "Weber",
    "Position": "Systemadministrator",
    "Department": "IT-Betrieb",
    "Email": "t.weber@techcorp.de",
    "Phone": "+49 89 12345-302"
  },
  {
    "ID": "cdb2fb76-0666-5752-92e0-15dde2280566",
    "CustomerID": "e526775a-b370-5a20-8350-ee7b596af4f4",
    "FirstName": "Klaus",
    "LastName": "Meyer",
    "Position": "Sachbearbeiter",
    "Department": "Vertrieb",
    "Email": "k.meyer@techcorp.de",
    "Phone": "+49 89 12345-303"
  },
  {
    "ID": "d8dd023b-8bc7-543b-aa1e-3406a27ffc28",
    "CustomerID": "e526775a-b370-5a20-8350-ee7b596af4f4",
    "FirstName": "Anna",
    "LastName": "Fischer",
    "Position": "Marketing-Managerin",
    "Department": "Marketing",
    "Email": "a.fischer@techcorp.de",
    "Phone": "+49 89 12345-304"
  },
  {
    "ID": "c89b9237-28e3-5bf5-a6f0-3d78157e9fef",
    "CustomerID": "e526775a-b370-5a20-8350-ee7b596af4f4",
    "FirstName": "Peter",
    "LastName": "Braun",
    "Position": "Softwareentwickler",
    "Department": "Entwicklung",
    "Email": "p.braun@techcorp.de",
    "Phone": "+49 89 12345-305"
  },
  {
    "ID": "f8840411-27a7-5fde-95eb-cc85e17ec00e",
    "CustomerID": "e526775a-b370-5a20-8350-ee7b596af4f4",
    "FirstName": "Julia",
    "LastName": "Hofmann",
    "Position": "Sachbearbeiterin",
    "Department": "Buchhaltung",
    "Email": "j.hofmann@techcorp.de",
    "Phone": "+49 89 12345-306"
  },
  {
    "ID": "de4db8b6-85c7-5c78-a345-ecc6a22ff12a",
    "CustomerID": "e526775a-b370-5a20-8350-ee7b596af4f4",
    "FirstName": "Lisa",
    "LastName": "Müller",
    "Position": "IT-Administratorin",
    "Department": "IT-Betrieb",
    "Email": "l.mueller@techcorp.de",
    "Phone": "+49 89 12345-307"
  },
  {
    "ID": "2a66bbbb-8f0d-5885-99b6-acc25927e58a",
    "CustomerID": "e526775a-b370-5a20-8350-ee7b596af4f4",
    "FirstName": "Hans",
    "LastName": "Wagner",
    "Position": "IT-Leiter",
    "Department": "IT-Management",
    "Email": "h.wagner@techcorp.de",
    "Phone": "+49 89 12345-308"
  }
]